szifi/.DS_Store
szifi/__init__.py
szifi/cat.py
szifi/example.py
szifi/expt.py
szifi/inpaint.py
szifi/maps.py
szifi/mmf.py
szifi/model.py
szifi/plotter.py
szifi/sim.py
szifi/sphere.py
szifi/websky.py
szifi-0.1.3.dist-info/METADATA
szifi-0.1.3.dist-info/WHEEL
szifi-0.1.3.dist-info/licenses/LICENSE
szifi-0.1.3.dist-info/RECORD
