Metadata-Version: 2.1
Name: szifi
Version: 0.1.3
Summary: Sunyaev-Zeldovich iterative Finder
Project-URL: Homepage, https://github.com/inigozubeldia/szifi
Project-URL: Bug Tracker, https://github.com/inigozubeldia/szifi/issues
Author-email: Inigo Zubeldia <zubeldiainigo@gmail.com>
License-File: LICENSE
Classifier: License :: OSI Approved :: MIT License
Classifier: Operating System :: OS Independent
Classifier: Programming Language :: Python :: 3
Requires-Python: >=3.7
